MANIFEST.in
README.rst
license.rst
setup.py
doc/Makefile
doc/conf.py
doc/index.rst
doc/license.rst
doc/api/asttools.rst
doc/api/bytecodetools.rst
doc/api/decompile.rst
doc/api/index.rst
meta/__init__.py
meta/testing.py
meta/utils.py
meta.egg-info/PKG-INFO
meta.egg-info/SOURCES.txt
meta.egg-info/dependency_links.txt
meta.egg-info/entry_points.txt
meta.egg-info/top_level.txt
meta/asttools/__init__.py
meta/asttools/mutators/__init__.py
meta/asttools/mutators/prune_mutator.py
meta/asttools/mutators/remove_trivial.py
meta/asttools/mutators/replace_mutator.py
meta/asttools/tests/__init__.py
meta/asttools/tests/test_conditional_symbols.py
meta/asttools/tests/test_depgraph.py
meta/asttools/tests/test_prune.py
meta/asttools/tests/test_remove_trivial.py
meta/asttools/tests/test_replace.py
meta/asttools/tests/test_sourcegen.py
meta/asttools/tests/test_symbol_visitor.py
meta/asttools/visitors/__init__.py
meta/asttools/visitors/cond_symbol_visitor.py
meta/asttools/visitors/copy_tree.py
meta/asttools/visitors/graph_visitor.py
meta/asttools/visitors/print_visitor.py
meta/asttools/visitors/pysourcegen.py
meta/asttools/visitors/symbol_visitor.py
meta/bytecodetools/__init__.py
meta/bytecodetools/bytecode_consumer.py
meta/bytecodetools/disassembler_.py
meta/bytecodetools/instruction.py
meta/bytecodetools/print_code.py
meta/bytecodetools/pyc_file.py
meta/decompiler/__init__.py
meta/decompiler/control_flow_instructions.py
meta/decompiler/disassemble.py
meta/decompiler/instructions.py
meta/decompiler/recompile.py
meta/decompiler/simple_instructions.py
meta/decompiler/util.py
meta/decompiler/tests/__init__.py
meta/decompiler/tests/test_comprehensions.py
meta/decompiler/tests/test_decompiler.py
meta/decompiler/tests/test_simple.py
meta/scripts/__init__.py
meta/scripts/depyc.py